{
  "screen_name": "settings_updates_submenu",
  "status_bar": "default",
  "windowed_canvas": false,
  "cache_canvases": false,
  "button_map": {
    "a": "select",
    "b": "back",
    "up": "previous",
    "down": "next",
    "left": "back",
    "right": "noop"
  },
  "background": {
    "layers": [
      {
        "image_path": "assets/settings_bg.png",
        "x": 0,
        "y": 0
      },
      {
        "image_path": "assets/divright_settings.png",
        "x": 140,
        "y": 50
      },
      {
        "text": "Clock",
        "x": 10,
        "y": 50,
        "text_color_palette": "settings_dim"
      },
      {
        "text": "GPS",
        "x": 10,
        "y": 85,
        "text_color_palette": "settings_dim"
      },
      {
        "text": "Updates",
        "x": 10,
        "y": 120,
        "text_color_palette": "settings_accent"
      },
      {
        "text": "Help",
        "x": 10,
        "y": 155,
        "text_color_palette": "settings_dim"
      },
      {
        "text": "About",
        "x": 10,
        "y": 190,
        "text_color_palette": "settings_dim"
      }
    ]
  },
  "pages": [
    {
      "page_index": 0,
      "menu_items": [
        {
          "id": "CurrentVersion",
          "x": 170,
          "y": 50,
          "unselectable": true,
          "layers": [
            {
              "text": "Current Version:",
              "text_color_palette": "settings_text"
            },
            {
              "variable_name": "$_FIRMWARE_VERSION",
              "string_template": {
                "text_size": "medium",
                "text_color_palette": "settings_text",
                "max_chars": 24,
                "wrap_text": false,
                "max_lines": 1
              },
              "x": 221
            }
          ]
        },
        {
          "id": "Check for Updates",
          "x": 170,
          "y": 85,
          "layers": [
            {
              "image_path": "assets/wizard.png"
            },
            {
              "text": "Check for Updates",
              "x": 40,
              "text_color_palette": "settings_text"
            }
          ],
          "selected_layers": [
            {
              "image_path": "assets/wizard.png"
            },
            {
              "text": "Check for Updates",
              "x": 40,
              "text_color_palette": "white"
            }
          ],
          "target": "check_for_updates"
        }
      ]
    }
  ]
}
